morethemes/__init__.py
morethemes/main.py
morethemes/preview.py
morethemes/themes.py
morethemes-0.5.1.dist-info/licenses/LICENSE
morethemes-0.5.1.dist-info/METADATA
morethemes-0.5.1.dist-info/WHEEL
morethemes-0.5.1.dist-info/top_level.txt
morethemes-0.5.1.dist-info/RECORD
