Metadata-Version: 2.4
Name: morethemes
Version: 0.5.1
Summary: More themes for matplotlib
Author-email: Joseph Barbier <joseph.barbierdarnal@gmail.com>
License-Expression: MIT
Project-URL: Homepage, https://y-sunflower.github.io/morethemes/
Project-URL: Issues, https://github.com/y-sunflower/morethemes/issues
Project-URL: Documentation, https://y-sunflower.github.io/morethemes/
Project-URL: Repository, https://github.com/y-sunflower/morethemes
Keywords: matplotlib,themes,style,colors
Classifier: Programming Language :: Python :: 3
Classifier: Operating System :: OS Independent
Classifier: Framework :: Matplotlib
Requires-Python: >=3.9
License-File: LICENSE
Requires-Dist: matplotlib>=3.6.0
Requires-Dist: pyfonts>=1.0.0
Dynamic: license-file
